django_enumfield_named_choices/__init__.py
django_enumfield_named_choices/enum.py
django_enumfield_named_choices/exceptions.py
django_enumfield_named_choices/models.py
django_enumfield_named_choices/validators.py
django_enumfield_named_choices/contrib/__init__.py
django_enumfield_named_choices/contrib/drf.py
django_enumfield_named_choices/db/__init__.py
django_enumfield_named_choices/db/fields.py
django_enumfield_named_choices/tests/__init__.py
django_enumfield_named_choices/tests/models.py
django_enumfield_named_choices/tests/test_enum.py
django_enumfield_named_choices/tests/test_settings.py
django_enumfield_named_choices/tests/test_validators.py
django_enumfield_named_choices/tests/urls.py
django_enumfield_named_choices-1.0a2.data/data/django_enumfield_named_choices/__pycache__/__init__.cpython-37.pyc
django_enumfield_named_choices-1.0a2.data/data/django_enumfield_named_choices/__pycache__/enum.cpython-37.pyc
django_enumfield_named_choices-1.0a2.data/data/django_enumfield_named_choices/__pycache__/exceptions.cpython-37.pyc
django_enumfield_named_choices-1.0a2.data/data/django_enumfield_named_choices/__pycache__/models.cpython-37.pyc
django_enumfield_named_choices-1.0a2.data/data/django_enumfield_named_choices/__pycache__/validators.cpython-37.pyc
django_enumfield_named_choices-1.0a2.data/data/django_enumfield_named_choices/contrib/__pycache__/__init__.cpython-37.pyc
django_enumfield_named_choices-1.0a2.data/data/django_enumfield_named_choices/contrib/__pycache__/drf.cpython-37.pyc
django_enumfield_named_choices-1.0a2.data/data/django_enumfield_named_choices/db/__pycache__/__init__.cpython-37.pyc
django_enumfield_named_choices-1.0a2.data/data/django_enumfield_named_choices/db/__pycache__/fields.cpython-37.pyc
django_enumfield_named_choices-1.0a2.data/data/django_enumfield_named_choices/tests/__pycache__/__init__.cpython-37.pyc
django_enumfield_named_choices-1.0a2.data/data/django_enumfield_named_choices/tests/__pycache__/models.cpython-37.pyc
django_enumfield_named_choices-1.0a2.dist-info/AUTHORS
django_enumfield_named_choices-1.0a2.dist-info/AUTHORS_ORIGINAL_WORK
django_enumfield_named_choices-1.0a2.dist-info/LICENSE
django_enumfield_named_choices-1.0a2.dist-info/LICENSE_ORIGINAL_WORK
django_enumfield_named_choices-1.0a2.dist-info/METADATA
django_enumfield_named_choices-1.0a2.dist-info/WHEEL
django_enumfield_named_choices-1.0a2.dist-info/top_level.txt
django_enumfield_named_choices-1.0a2.dist-info/RECORD
