Metadata-Version: 2.1
Name: django-enumfield-named-choices
Version: 1.0a2
Summary: Custom Django field for using enumerations of named constants
Home-page: http://github.com/kolotev/django-enumfield-named-choices
Author: Andrey Kolotev
Author-email: kolotev@gmail.com
License: MIT
Download-URL: https://github.com/kolotev/django-enumfield-named-choices/tarball/1.0a2
Keywords: django,enum,field,status,state,choices,form,model
Platform: any
Classifier: Programming Language :: Python
Classifier: Programming Language :: Python :: 3.6
Classifier: Programming Language :: Python :: 3.7
Classifier: Framework :: Django
Classifier: Natural Language :: English
Classifier: Environment :: Web Environment
Classifier: Intended Audience :: Developers
Classifier: License :: OSI Approved :: MIT License
Classifier: Operating System :: OS Independent
Classifier: Topic :: Utilities
Classifier: Topic :: Software Development :: Libraries :: Python Modules
